LICENSE
MANIFEST.in
README.md
setup.py
django_ga_puller.egg-info/PKG-INFO
django_ga_puller.egg-info/SOURCES.txt
django_ga_puller.egg-info/dependency_links.txt
django_ga_puller.egg-info/requires.txt
django_ga_puller.egg-info/top_level.txt
ga_puller/__init__.py
ga_puller/models.py
ga_puller/tests.py
ga_puller/urls.py
ga_puller/views.py
ga_puller/management/__init__.py
ga_puller/management/commands/__init__.py
ga_puller/management/commands/analytics_import.py