Metadata-Version: 1.1
Name: django-ga-puller
Version: 0.1.3
Summary: Django app used to pull daily Google Analytics data into your django database.
Home-page: https://github.com/CIGIHub/django-ga-puller/
Author: Caroline Simpson
Author-email: csimpson@cigionline.org
License: MIT License
Platform: UNKNOWN
Classifier: Environment :: Web Environment
Classifier: Framework :: Django
Classifier: Intended Audience :: Developers
Classifier: License :: OSI Approved :: MIT License
Classifier: Operating System :: OS Independent
Classifier: Programming Language :: Python
Classifier: Programming Language :: Python :: 2
Classifier: Topic :: Internet :: WWW/HTTP
Classifier: Topic :: Internet :: WWW/HTTP :: Dynamic Content
